setup.py
Mlask.egg-info/PKG-INFO
Mlask.egg-info/SOURCES.txt
Mlask.egg-info/dependency_links.txt
Mlask.egg-info/requires.txt
Mlask.egg-info/top_level.txt
mlask/__init__.py
mlask/bin/mlask-admin.py
mlask/conf/__init__.py
mlask/conf/empty_config.py
mlask/conf/empty_app/__init__.py
mlask/conf/empty_app/config.py
mlask/conf/empty_app/manage.py
mlask/conf/empty_app/tests.py
mlask/conf/empty_app/views.py
mlask/management/__init__.py
mlask/management/input_parser.py
mlask/management/commands/__init__.py
mlask/management/commands/basic_commands.py
mlask/management/commands/startapp.py
mlask/management/commands/test.py