Metadata-Version: 1.1
Name: Mlask
Version: 0.2
Summary: manage.py for Flask
Home-page: https://github.com/hamaxx/mlask
Author: Jure Ham
Author-email: jure.ham@zemanta.com
License: BSD
Platform: UNKNOWN
Classifier: Development Status :: 3 - Alpha
